glia/__init__.py
glia/__main__.py
glia/app.py
glia/definitions.py
glia/cli/__init__.py
glia/cli/start.py
glia/widgets/__init__.py
glia/widgets/jupyter.py
glia/widgets/editor/__init__.py
glia/widgets/editor/tabs.py
glia/widgets/editor/lexers/__init__.py
glia/widgets/editor/lexers/python.py
glia/windows/__init__.py
glia/windows/main.py
Glia-0.1.0.dev6.dist-info/AUTHORS.rst
Glia-0.1.0.dev6.dist-info/LICENSE
Glia-0.1.0.dev6.dist-info/METADATA
Glia-0.1.0.dev6.dist-info/WHEEL
Glia-0.1.0.dev6.dist-info/entry_points.txt
Glia-0.1.0.dev6.dist-info/top_level.txt
Glia-0.1.0.dev6.dist-info/RECORD
