Metadata-Version: 2.1
Name: Glia
Version: 0.1.0.dev6
Summary: Official Desktop Client for Glial Engines
Home-page: https://github.com/GliaHQ/Glia
Author: daegontaven
Author-email: daegontaven@gmail.com
License: Apache License 2.0
Platform: UNKNOWN
Classifier: Development Status :: 1 - Planning
Classifier: Intended Audience :: Science/Research
Classifier: Intended Audience :: End Users/Desktop
Classifier: License :: OSI Approved :: Apache Software License
Classifier: Natural Language :: English
Classifier: Operating System :: OS Independent
Classifier: Programming Language :: Python :: 3.7
Classifier: Environment :: X11 Applications :: Qt
Classifier: Topic :: Documentation :: Sphinx
Requires-Python: >=3.7
Requires-Dist: PyQt5
Requires-Dist: QScintilla
Requires-Dist: qtconsole
Provides-Extra: docs
Requires-Dist: Sphinx ; extra == 'docs'
Requires-Dist: sphinx-rtd-theme ; extra == 'docs'
Provides-Extra: tests
Requires-Dist: pytest ; extra == 'tests'
Requires-Dist: pytest-qt ; extra == 'tests'
Requires-Dist: pytest-cov ; extra == 'tests'
Requires-Dist: pytest-runner ; extra == 'tests'
